webpageinfo/__init__.py
webpageinfo/browser.py
webpageinfo/page.py
webpageinfo/safe_html.py
webpageinfo/config/__init__.py
webpageinfo/config/ignored_html_tags.py
webpageinfo/config/ignored_word_in_tags.py
webpageinfo/config/rejected_content_class.py
webpageinfo/config/rejected_content_id.py
webpageinfo/config/removed_html_tags.py
webpageinfo/config/simple_html_tags.py
webpageinfo/config/svg_tags.py
webpageinfo-2024.2.2.dist-info/METADATA
webpageinfo-2024.2.2.dist-info/WHEEL
webpageinfo-2024.2.2.dist-info/licenses/LICENSE
webpageinfo-2024.2.2.dist-info/RECORD
